oxDNA_analysis_tools/__init__.py
oxDNA_analysis_tools/align.py
oxDNA_analysis_tools/anm_parameterize.py
oxDNA_analysis_tools/backbone_flexibility.py
oxDNA_analysis_tools/bond_analysis.py
oxDNA_analysis_tools/centroid.py
oxDNA_analysis_tools/clustering.py
oxDNA_analysis_tools/config.py
oxDNA_analysis_tools/contact_map.py
oxDNA_analysis_tools/db_to_force.py
oxDNA_analysis_tools/deviations.py
oxDNA_analysis_tools/distance.py
oxDNA_analysis_tools/duplex_angle_plotter.py
oxDNA_analysis_tools/duplex_finder.py
oxDNA_analysis_tools/entry.py
oxDNA_analysis_tools/forces2pairs.py
oxDNA_analysis_tools/generate_force.py
oxDNA_analysis_tools/mean.py
oxDNA_analysis_tools/minify.py
oxDNA_analysis_tools/multidimensional_scaling_mean.py
oxDNA_analysis_tools/output_bonds.py
oxDNA_analysis_tools/oxDNA_PDB.py
oxDNA_analysis_tools/oxDNA_PDB2.py
oxDNA_analysis_tools/pca.py
oxDNA_analysis_tools/plot_energy.py
oxDNA_analysis_tools/subset_trajectory.py
oxDNA_analysis_tools/superimpose.py
oxDNA_analysis_tools/UTILS/RyeReader.py
oxDNA_analysis_tools/UTILS/__init__.py
oxDNA_analysis_tools/UTILS/base.py
oxDNA_analysis_tools/UTILS/chunksize.py
oxDNA_analysis_tools/UTILS/data_structures.py
oxDNA_analysis_tools/UTILS/dd12_na.pdb
oxDNA_analysis_tools/UTILS/geom.py
oxDNA_analysis_tools/UTILS/get_confs.cpython-311-darwin.so
oxDNA_analysis_tools/UTILS/model.h
oxDNA_analysis_tools/UTILS/oat_multiprocesser.py
oxDNA_analysis_tools/UTILS/pdb.py
oxDNA_analysis_tools/UTILS/protein_to_pdb.py
oxDNA_analysis_tools/UTILS/readers.py
oxDNA_analysis_tools/UTILS/rna_model.h
oxDNA_analysis_tools/UTILS/utils.py
oxDNA_analysis_tools/cython_utils/get_confs.c
oxDNA_analysis_tools/cython_utils/get_confs.pyx
oxDNA_analysis_tools/external_force_utils/__init__.py
oxDNA_analysis_tools/external_force_utils/exclude_force.py
oxDNA_analysis_tools/external_force_utils/force_reader.py
oxDNA_analysis_tools/external_force_utils/forces.py
oxDNA_analysis_tools-2.0.5.dist-info/LICENSE
oxDNA_analysis_tools-2.0.5.dist-info/METADATA
oxDNA_analysis_tools-2.0.5.dist-info/WHEEL
oxDNA_analysis_tools-2.0.5.dist-info/entry_points.txt
oxDNA_analysis_tools-2.0.5.dist-info/top_level.txt
oxDNA_analysis_tools-2.0.5.dist-info/RECORD
