Metadata-Version: 2.1
Name: oxDNA_analysis_tools
Version: 2.0.5
Summary: Python scripts and libraries for structural analysis of oxDNA simulations.
Home-page: https://github.com/sulcgroup/oxdna_analysis_tools
Author: Erik Poppleton
Author-email: epopplet@asu.edu
Project-URL: Bug Tracker, https://github.com/sulcgroup/oxdna_analysis_tools/issues
Classifier: Programming Language :: Python :: 3
Classifier: License :: OSI Approved :: GNU General Public License v3 (GPLv3)
Classifier: Operating System :: OS Independent
Requires-Python: >=3.8
License-File: LICENSE
Requires-Dist: numpy>1.16
Requires-Dist: scikit-learn>0.21.2
Requires-Dist: matplotlib>3.0.0
Requires-Dist: biopython>1.73
